dictionary/__init__.py
dictionary/dictionary.py
maryam_shahid_dictionary-2.0.2.dist-info/METADATA
maryam_shahid_dictionary-2.0.2.dist-info/WHEEL
maryam_shahid_dictionary-2.0.2.dist-info/top_level.txt
maryam_shahid_dictionary-2.0.2.dist-info/RECORD
