Metadata-Version: 2.1
Name: maryam-shahid-dictionary
Version: 2.0.2
Summary: UNKNOWN
Author: Maryam Shahid
License: UNKNOWN
Platform: UNKNOWN
Requires-Python: >=3.8
Requires-Dist: requests (>=2.23.0)
